qp/__init__.py
qp/_version.py
qp/conversion_funcs.py
qp/dict_utils.py
qp/ensemble.py
qp/factory.py
qp/hist_pdf.py
qp/interp_pdf.py
qp/metrics.py
qp/mixmod_pdf.py
qp/pdf_gen.py
qp/plotting.py
qp/quant_pdf.py
qp/scipy_pdfs.py
qp/sparse_pdf.py
qp/sparse_rep.py
qp/spline_pdf.py
qp/test_data.py
qp/test_funcs.py
qp/utils.py
qp/version.py
pz_qp_temp-0.6.2.dist-info/LICENSE
pz_qp_temp-0.6.2.dist-info/METADATA
pz_qp_temp-0.6.2.dist-info/WHEEL
pz_qp_temp-0.6.2.dist-info/top_level.txt
pz_qp_temp-0.6.2.dist-info/RECORD
