Metadata-Version: 2.1
Name: pz-qp-temp
Version: 0.6.2
Summary: Quantile parametrization of probability distribution functions
Home-page: https://github.com/LSSTDESC/qp
Author: Alex Malz, Phil Marshall, Eric Charles
Author-email: aimalz@nyu.edu, pjm@slac.stanford.edu, echarles@slac.stanford.edu
Classifier: Development Status :: 4 - Beta
Classifier: License :: OSI Approved :: MIT License
Classifier: Intended Audience :: Developers
Classifier: Intended Audience :: Science/Research
Classifier: Operating System :: OS Independent
Classifier: Programming Language :: Python
License-File: LICENSE
Requires-Dist: matplotlib
Requires-Dist: numpy
Requires-Dist: scipy (>=1.9.0)
Requires-Dist: scikit-learn
Requires-Dist: tables-io (>=0.7.7)
